isearch.py
similar_search-0.1.1.dist-info/LICENSE
similar_search-0.1.1.dist-info/METADATA
similar_search-0.1.1.dist-info/WHEEL
similar_search-0.1.1.dist-info/entry_points.txt
similar_search-0.1.1.dist-info/top_level.txt
similar_search-0.1.1.dist-info/RECORD
