Metadata-Version: 2.1
Name: similar-search
Version: 0.1.1
Summary: An image search tool to find similar images on your disk.
Home-page: https://github.com/seamile/isearch
Author: Seamile
Author-email: lanhuermao@gmail.com
Classifier: Programming Language :: Python :: 3
Classifier: License :: OSI Approved :: MIT License
Classifier: Operating System :: MacOS :: MacOS X
Classifier: Operating System :: POSIX
Classifier: Topic :: Internet
Classifier: Topic :: Utilities
Requires-Python: >=3.6
License-File: LICENSE
Requires-Dist: filetype (>=1.2.0)
Requires-Dist: numpy (>=1.24.2)
Requires-Dist: Pillow (>=9.4.0)
Requires-Dist: scipy (>=1.10.1)
